torch_graph_force/__init__.py
torch_graph_force/benchmark.py
torch_graph_force/data.py
torch_graph_force/layout.py
torch_graph_force/model.py
torch_graph_force/utils.py
torch_graph_force-0.1.1.dist-info/LICENSE.md
torch_graph_force-0.1.1.dist-info/METADATA
torch_graph_force-0.1.1.dist-info/WHEEL
torch_graph_force-0.1.1.dist-info/top_level.txt
torch_graph_force-0.1.1.dist-info/RECORD
