Metadata-Version: 2.1
Name: torch-graph-force
Version: 0.1.1
Summary: Force-directed layouts for Large Graphs with GPU acceleration
Author-email: Tin Nguyen <trung.tin.nguyen0309@gmail.com>
Keywords: graph,layout,force-directed,pytorch
Classifier: Programming Language :: Python :: Implementation :: CPython
Classifier: Topic :: Scientific/Engineering :: Visualization
Classifier: License :: OSI Approved :: MIT License
Requires-Python: >=3.8
License-File: LICENSE.md
Requires-Dist: numpy
Requires-Dist: scipy
Requires-Dist: pandas
Requires-Dist: networkx
Requires-Dist: tqdm
